test_api_5/__init__.py
test_api_5/example.py
test_api_5/scripts.py
test_api_5-0.0.1.dist-info/METADATA
test_api_5-0.0.1.dist-info/WHEEL
test_api_5-0.0.1.dist-info/entry_points.txt
test_api_5-0.0.1.dist-info/top_level.txt
test_api_5-0.0.1.dist-info/RECORD
